README.rst
setup.py
sqlnosql/__init__.py
sqlnosql/commands.py
sqlnosql/formats.py
sqlnosql/migration.py
sqlnosql/schema.py
sqlnosql/serializers.py
sqlnosql/utils.py
sqlnosql/validation.py
sqlnosql.egg-info/PKG-INFO
sqlnosql.egg-info/SOURCES.txt
sqlnosql.egg-info/dependency_links.txt
sqlnosql.egg-info/requires.txt
sqlnosql.egg-info/top_level.txt