Metadata-Version: 1.1
Name: sqlnosql
Version: 0.2.0
Summary: Push semi-structured data (e.g. JSON documents) into a database with a minimum of fuss. Includes validation and schema migration.
Home-page: UNKNOWN
Author: Stijn Debrouwere
Author-email: stijn@stdout.be
License: ISC
Download-URL: http://www.github.com/newslynx/nosqlsql/tarball/master
Keywords: etl sql nosql postgres migrations transform load extract
Platform: UNKNOWN
Classifier: Development Status :: 3 - Alpha
Classifier: Intended Audience :: Developers
Classifier: License :: OSI Approved :: MIT License
Classifier: Operating System :: OS Independent
Classifier: Programming Language :: Python
Classifier: Topic :: Utilities
